[
  {
    "Username": "Russel",
    "Gender": "male",
    "DateOfBirth": "1995-11-16",
    "Password": "password",
    "KnownAs": "Russel Murad",
    "Created": "2020-08-02",
    "LastActive": "2020-08-02",
    "Introduction": "None",
    "LookingFor": "None",
    "Interests": "None",
    "City": "Dhaka",
    "Country": "Bangladesh",
    "Photos": [
      {
        "url": "https://res.cloudinary.com/djysg4anm/image/upload/v1595710529/109412934_3276113449281532_1444262762608654509_o_uc0ahr.jpg",
        "isMain": true,
        "description": "None"
      }
    ]
  },
  {
    "Username": "Sabrina",
    "Gender": "female",
    "DateOfBirth": "1996-04-19",
    "Password": "password",
    "KnownAs": "Sabrina Jenis Sawrna",
    "Created": "2020-01-21",
    "LastActive": "2020-01-21",
    "Introduction": "None",
    "LookingFor": "None",
    "Interests": "None.",
    "City": "Dhaka",
    "Country": "Bangladesh",
    "Photos": [
      {
        "url": "https://res.cloudinary.com/djysg4anm/image/upload/v1595710486/106982434_583654135625112_7755762880045109209_n_yhpqid.jpg",
        "isMain": true,
        "description": ""
      }
    ]
  },
 
  {
    "Username": "Shahnaz",
    "Gender": "male",
    "DateOfBirth": "1997-12-05",
    "Password": "password",
    "KnownAs": "Shahnaz Sharkar",
    "Created": "2020-06-24",
    "LastActive": "2020-06-24",
    "Introduction": "None",
    "LookingFor": "None",
    "Interests": "None",
    "City": "Dhaka",
    "Country": "Bangladesh",
    "Photos": [
      {
        "url": "https://res.cloudinary.com/djysg4anm/image/upload/v1595710486/106401468_1158184161195734_6110849682787364332_n_rk6u67.jpg",
        "isMain": true,
        "description": "None."
      }
    ]
  },

  
  {
    "Username": "Sharkar",
    "Gender": "female",
    "DateOfBirth": "1997-12-05",
    "Password": "password",
    "KnownAs": "Shahnaz Sharkar",
    "Created": "2020-06-24",
    "LastActive": "2020-06-24",
    "Introduction": "None",
    "LookingFor": "None",
    "Interests": "None",
    "City": "Dhaka",
    "Country": "Bangladesh",
    "Photos": [
      {
        "url": "https://res.cloudinary.com/djysg4anm/image/upload/v1595710486/106401468_1158184161195734_6110849682787364332_n_rk6u67.jpg",
        "isMain": true,
        "description": "None."
      }
    ]
  },

  {
    "Username": "Tonu",
    "Gender": "female",
    "DateOfBirth": "1997-02-25",
    "Password": "password",
    "KnownAs": "Afsana Hoque Tonu",
    "Created": "2020-07-17",
    "LastActive": "2020-07-17",
    "Introduction": "None",
    "LookingFor": "None",
    "Interests": "None",
    "City": "Dhaka",
    "Country": "Bangladesh",
    "Photos": [
      {
        "url": "https://res.cloudinary.com/djysg4anm/image/upload/v1595710671/106671102_704146260161654_7723987645503431429_n_f5ev64.jpg",
        "isMain": true,
        "description": "None."
      }
    ]
  },
  {
    "Username": "Sanjida",
    "Gender": "male",
    "DateOfBirth": "1997-03-01",
    "Password": "password",
    "KnownAs": "Sanjida Ishrat",
    "Created": "2020-03-25",
    "LastActive": "2020-03-25",
    "Introduction": "None",
    "LookingFor": "None",
    "Interests": "None.",
    "City": "Dhaka",
    "Country": "Bangladesh",
    "Photos": [
      {
        "url": "https://res.cloudinary.com/djysg4anm/image/upload/v1595710486/106411996_128751025550488_693916134996247230_n_gdcwrc.jpg",
        "isMain": true,
        "description": "None."
      }
    ]
  },

  {
    "Username": "Rifa",
    "Gender": "female",
    "DateOfBirth": "1997-08-21",
    "Password": "password",
    "KnownAs": "Rifa Nanzeeba",
    "Created": "2020-08-03",
    "LastActive": "2020-08-03",
    "Introduction": "None",
    "LookingFor": "None",
    "Interests": "None.",
    "City": "Dhaka",
    "Country": "Bangladesh",
    "Photos": [
      {
        "url": "https://res.cloudinary.com/djysg4anm/image/upload/v1595710486/84408229_182459516171612_8419974197702295552_o_h25cvt.jpg",
        "isMain": true,
        "description": "None."
      }
    ]
  },
  {
    "Username": "Nanzeeba",
    "Gender": "male",
    "DateOfBirth": "1997-08-21",
    "Password": "password",
    "KnownAs": "Rifa Nanzeeba",
    "Created": "2020-08-03",
    "LastActive": "2020-08-03",
    "Introduction": "None",
    "LookingFor": "None",
    "Interests": "None.",
    "City": "Dhaka",
    "Country": "Bangladesh",
    "Photos": [
      {
        "url": "https://res.cloudinary.com/djysg4anm/image/upload/v1595710486/84408229_182459516171612_8419974197702295552_o_h25cvt.jpg",
        "isMain": true,
        "description": "None."
      }
    ]
  },
  


  {
    "Username": "Nisha",
    "Gender": "female",
    "DateOfBirth": "1997-08-15",
    "Password": "password",
    "KnownAs": "Johora Nisha",
    "Created": "2020-02-17",
    "LastActive": "2020-02-17",
    "Introduction": "None",
    "LookingFor": "None",
    "Interests": "None.",
    "City": "Dhaka",
    "Country": "Bangladesh",
    "Photos": [
      {
        "url": "https://res.cloudinary.com/djysg4anm/image/upload/v1595710484/56158070_372582593344356_4787577852755181568_n_bsg04e.jpg",
        "isMain": true,
        "description": "None."
      }
    ]
  },
  {
  
    "Username": "Fatema",
    "Gender": "male",
    "DateOfBirth": "1997-08-15",
    "Password": "password",
    "KnownAs": "Fatema Ahmad",
    "Created": "2020-02-17",
    "LastActive": "2020-02-17",
    "Introduction": "None",
    "LookingFor": "None",
    "Interests": "None.",
    "City": "Dhaka",
    "Country": "Bangladesh",
    "Photos": [
      {
        "url": "https://res.cloudinary.com/djysg4anm/image/upload/v1595710862/anime_741831_vcreff.jpg",
        "isMain": true,
        "description": "None."
      }
    ]
  },
  {
    "Username": "Ritu",
    "Gender": "female",
    "DateOfBirth": "1997-08-15",
    "Password": "password",
    "KnownAs": "Sanjida Islam",
    "Created": "2020-02-17",
    "LastActive": "2020-02-17",
    "Introduction": "None",
    "LookingFor": "None",
    "Interests": "None.",
    "City": "Dhaka",
    "Country": "Bangladesh",
    "Photos": [
      {
        "url": "https://res.cloudinary.com/djysg4anm/image/upload/v1595710484/57447264_2117494581701031_2068196928218202112_o_s67s6o.jpg",
        "isMain": true,
        "description": "None."
      }
    ]
  },
  {
    "Username": "Mim",
    "Gender": "female",
    "DateOfBirth": "1997-08-15",
    "Password": "password",
    "KnownAs": "Mim Jannat",
    "Created": "2020-02-17",
    "LastActive": "2020-02-17",
    "Introduction": "None",
    "LookingFor": "None",
    "Interests": "None.",
    "City": "Dhaka",
    "Country": "Bangladesh",
    "Photos": [
      {
        "url": "https://res.cloudinary.com/djysg4anm/image/upload/v1595710485/81107556_2579396052346869_5248112962383642624_n_s504qw.jpg",
        "isMain": true,
        "description": "None."
      }
    ]
  },
  {
    "Username": "Jannat",
    "Gender": "male",
    "DateOfBirth": "1997-08-15",
    "Password": "password",
    "KnownAs": "Mim Jannat",
    "Created": "2020-02-17",
    "LastActive": "2020-02-17",
    "Introduction": "None",
    "LookingFor": "None",
    "Interests": "None.",
    "City": "Dhaka",
    "Country": "Bangladesh",
    "Photos": [
      {
        "url": "https://res.cloudinary.com/djysg4anm/image/upload/v1595710485/81107556_2579396052346869_5248112962383642624_n_s504qw.jpg",
        "isMain": true,
        "description": "None."
      }
    ]
  },
  {
    "Username": "Salma",
    "Gender": "male",
    "DateOfBirth": "1997-08-15",
    "Password": "password",
    "KnownAs": "Umma Salma",
    "Created": "2020-02-17",
    "LastActive": "2020-02-17",
    "Introduction": "None",
    "LookingFor": "None",
    "Interests": "None.",
    "City": "Dhaka",
    "Country": "Bangladesh",
    "Photos": [
      {
        "url": "https://res.cloudinary.com/djysg4anm/image/upload/v1595710862/anime_741831_vcreff.jpg",
        "isMain": true,
        "description": "None."
      }
    ]
  },
  {
    "Username": "Debnath",
    "Gender": "female",
    "DateOfBirth": "1997-08-15",
    "Password": "password",
    "KnownAs": "Shuporna Debnath",
    "Created": "2020-02-17",
    "LastActive": "2020-02-17",
    "Introduction": "None",
    "LookingFor": "None",
    "Interests": "None.",
    "City": "Dhaka",
    "Country": "Bangladesh",
    "Photos": [
      {
        "url": "https://res.cloudinary.com/djysg4anm/image/upload/v1595711031/Screenshot_11_f2jwdb.png",
        "isMain": true,
        "description": "None."
      }
    ]
  },
  {
    "Username": "Akram",
    "Gender": "male",
    "DateOfBirth": "1997-08-15",
    "Password": "password",
    "KnownAs": "Akram Hossain Rikon",
    "Created": "2020-02-17",
    "LastActive": "2020-02-17",
    "Introduction": "None",
    "LookingFor": "None",
    "Interests": "None.",
    "City": "Dhaka",
    "Country": "Bangladesh",
    "Photos": [
      {
        "url": "https://res.cloudinary.com/djysg4anm/image/upload/v1595710486/86229105_2517870868319071_4994258877403889664_o_nnxcia.jpg",
        "isMain": true,
        "description": "None."
      }
    ]
  },
 
  {
    "Username": "Hossain",
    "Gender": "female",
    "DateOfBirth": "1996-09-07",
    "Password": "password",
    "KnownAs": "Nazmul Hossain",
    "Created": "2020-07-07",
    "LastActive": "2020-07-07",
    "Introduction": "None",
    "LookingFor": "None",
    "Interests": "None",
    "City": "Dhaka",
    "Country": "Bangladesh",
    "Photos": [
      {
        "url": "https://res.cloudinary.com/djysg4anm/image/upload/v1595710486/86171545_2811935165581137_7531044764909568000_o_zkxa8j.jpg",
        "isMain": true,
        "description": "None."
      }
    ]
  },
  {
    "Username": "Farhad",
    "Gender": "female",
    "DateOfBirth": "1997-03-07",
    "Password": "password",
    "KnownAs": "Farhad Hossain",
    "Created": "2020-08-22",
    "LastActive": "2020-08-22",
    "Introduction": "None",
    "LookingFor": "None",
    "Interests": "None",
    "City": "Dhaka",
    "Country": "Bangladesh",
    "Photos": [
      {
        "url": "https://res.cloudinary.com/djysg4anm/image/upload/v1595710485/64783439_2414391922153282_7343702586425344_o_oa93y2.jpg",
        "isMain": true,
        "description": "None."
      }
    ]
  },
  {
    "Username": "Shaikot",
    "Gender": "male",
    "DateOfBirth": "1997-08-06",
    "Password": "password",
    "KnownAs": "Anisur Rahman Shaikot",
    "Created": "2020-02-17",
    "LastActive": "2020-02-17",
    "Introduction": "None",
    "LookingFor": "None",
    "Interests": "None.",
    "City": "Dhaka",
    "Country": "Bangladesh",
    "Photos": [
      {
        "url": "https://res.cloudinary.com/djysg4anm/image/upload/v1595710862/anime_741831_vcreff.jpg",
        "isMain": true,
        "description": "None."
      }
    ]
  },
  {
    "Username": "Abid",
    "Gender": "female",
    "DateOfBirth": "1997-08-15",
    "Password": "password",
    "KnownAs": "Abid Hossain",
    "Created": "2020-02-17",
    "LastActive": "2020-02-17",
    "Introduction": "None",
    "LookingFor": "None",
    "Interests": "None.",
    "City": "Dhaka",
    "Country": "Bangladesh",
    "Photos": [
      {
        "url": "https://res.cloudinary.com/djysg4anm/image/upload/v1595710484/45361620_582184515571794_3920707586743074816_o_jayahv.jpg",
        "isMain": true,
        "description": "None."
      }
    ]
  },
  {
    "Username": "Nayan",
    "Gender": "female",
    "DateOfBirth": "1997-08-15",
    "Password": "password",
    "KnownAs": "Al Mamun Nayan",
    "Created": "2020-02-17",
    "LastActive": "2020-02-17",
    "Introduction": "None",
    "LookingFor": "None",
    "Interests": "None.",
    "City": "Dhaka",
    "Country": "Bangladesh",
    "Photos": [
      {
        "url": "https://res.cloudinary.com/djysg4anm/image/upload/v1595710487/115852490_1575050215988892_7717173362737984866_o_ul44b1.jpg",
        "isMain": true,
        "description": "None."
      }
    ]
  },
  {
    "Username": "Arefin",
    "Gender": "male",
    "DateOfBirth": "1997-08-15",
    "Password": "password",
    "KnownAs": "Arefin Shagor",
    "Created": "2020-02-17",
    "LastActive": "2020-02-17",
    "Introduction": "None",
    "LookingFor": "None",
    "Interests": "None.",
    "City": "Dhaka",
    "Country": "Bangladesh",
    "Photos": [
      {
        "url": "https://res.cloudinary.com/djysg4anm/image/upload/v1595710484/28870825_222419304985189_1664497163767382016_o_zsti0r.jpg",
        "isMain": true,
        "description": "None."
      }
    ]
  },
  {
    "Username": "Shishir",
    "Gender": "female",
    "DateOfBirth": "1997-08-15",
    "Password": "password",
    "KnownAs": "Shishir Choudhury",
    "Created": "2020-02-17",
    "LastActive": "2020-02-17",
    "Introduction": "None",
    "LookingFor": "None",
    "Interests": "None.",
    "City": "Dhaka",
    "Country": "Bangladesh",
    "Photos": [
      {
        "url": "https://res.cloudinary.com/djysg4anm/image/upload/v1595711201/81634170_480893889479406_8964021355808817152_n_tx7nu1.jpg",
        "isMain": true,
        "description": "None."
      }
    ]
  },
  {
    "Username": "Choudhury",
    "Gender": "male",
    "DateOfBirth": "1997-08-15",
    "Password": "password",
    "KnownAs": "Shishir Choudhury",
    "Created": "2020-02-17",
    "LastActive": "2020-02-17",
    "Introduction": "None",
    "LookingFor": "None",
    "Interests": "None.",
    "City": "Dhaka",
    "Country": "Bangladesh",
    "Photos": [
      {
        "url": "https://res.cloudinary.com/djysg4anm/image/upload/v1595711201/81634170_480893889479406_8964021355808817152_n_tx7nu1.jpg",
        "isMain": true,
        "description": "None."
      }
    ]
  },
  {
    "Username": "Asraf",
    "Gender": "male",
    "DateOfBirth": "1997-08-15",
    "Password": "password",
    "KnownAs": "Shahrukh Shishir",
    "Created": "2020-02-17",
    "LastActive": "2020-02-17",
    "Introduction": "None",
    "LookingFor": "None",
    "Interests": "None.",
    "City": "Dhaka",
    "Country": "Bangladesh",
    "Photos": [
      {
        "url": "https://res.cloudinary.com/djysg4anm/image/upload/v1595711297/93839060_1306321536244640_1654344694303293440_o_vvth4d.jpg",
        "isMain": true,
        "description": "None."
      }
    ]
  },
  {
    "Username": "Emdadul",
    "Gender": "male",
    "DateOfBirth": "1997-08-15",
    "Password": "password",
    "KnownAs": "Emdadul Hoque Tareque",
    "Created": "2020-02-17",
    "LastActive": "2020-02-17",
    "Introduction": "None",
    "LookingFor": "None",
    "Interests": "None.",
    "City": "Dhaka",
    "Country": "Bangladesh",
    "Photos": [
      {
        "url": "https://res.cloudinary.com/djysg4anm/image/upload/v1595710486/104537066_3070446413051200_5928982169474292780_o_nsx0gz.jpg",
        "isMain": true,
        "description": "None."
      }
    ]
  },
  {
    "Username": "Anik",
    "Gender": "female",
    "DateOfBirth": "1997-08-15",
    "Password": "password",
    "KnownAs": "Hussain Ahamed Anik",
    "Created": "2020-02-17",
    "LastActive": "2020-02-17",
    "Introduction": "None",
    "LookingFor": "None",
    "Interests": "None.",
    "City": "Dhaka",
    "Country": "Bangladesh",
    "Photos": [
      {
        "url": "https://res.cloudinary.com/djysg4anm/image/upload/v1595710485/57870594_2193007497456761_5418053947724136448_o_vcmddx.jpg",
        "isMain": true,
        "description": "None."
      }
    ]
  },
  {
    "Username": "Maruf",
    "Gender": "male",
    "DateOfBirth": "1997-08-15",
    "Password": "password",
    "KnownAs": "Maruf Yeasin",
    "Created": "2020-02-17",
    "LastActive": "2020-02-17",
    "Introduction": "None",
    "LookingFor": "None",
    "Interests": "None.",
    "City": "Dhaka",
    "Country": "Bangladesh",
    "Photos": [
      {
        "url": "https://res.cloudinary.com/djysg4anm/image/upload/v1595710486/90938278_228060178561477_90421963662557184_o_fwnm8w.jpg",
        "isMain": true,
        "description": "None."
      }
    ]
  },
  {
    "Username": "Mashrafe",
    "Gender": "male",
    "DateOfBirth": "1997-08-15",
    "Password": "password",
    "KnownAs": "Mashrafe Sinhaj",
    "Created": "2020-02-17",
    "LastActive": "2020-02-17",
    "Introduction": "None",
    "LookingFor": "None",
    "Interests": "None.",
    "City": "Dhaka",
    "Country": "Bangladesh",
    "Photos": [
      {
        "url": "https://res.cloudinary.com/djysg4anm/image/upload/v1595710485/78815169_156054182444655_5708245994353721344_o_bkt3ml.jpg",
        "isMain": true,
        "description": "None."
      }
    ]
  },
  {
    "Username": "Rana",
    "Gender": "female",
    "DateOfBirth": "1997-08-15",
    "Password": "password",
    "KnownAs": "Md Rana",
    "Created": "2020-02-17",
    "LastActive": "2020-02-17",
    "Introduction": "None",
    "LookingFor": "None",
    "Interests": "None.",
    "City": "Dhaka",
    "Country": "Bangladesh",
    "Photos": [
      {
        "url": "https://res.cloudinary.com/djysg4anm/image/upload/v1595710485/67386925_2284413808486190_3104257659805630464_n_cj2wmn.jpg",
        "isMain": true,
        "description": "None."
      }
    ]
  },
  {
    "Username": "Redwanuzzaman",
    "Gender": "male",
    "DateOfBirth": "1997-08-15",
    "Password": "password",
    "KnownAs": "Md Redwanuzzaman",
    "Created": "2020-02-17",
    "LastActive": "2020-02-17",
    "Introduction": "None",
    "LookingFor": "None",
    "Interests": "None.",
    "City": "Dhaka",
    "Country": "Bangladesh",
    "Photos": [
      {
        "url": "https://res.cloudinary.com/djysg4anm/image/upload/v1595710484/10254044_1095271833856418_878330304806517149_n_grupaj.jpg",
        "isMain": true,
        "description": "None."
      }
    ]
  },
  {
    "Username": "Bijoy",
    "Gender": "female",
    "DateOfBirth": "1997-08-15",
    "Password": "password",
    "KnownAs": "Nh Bijoy",
    "Created": "2020-02-17",
    "LastActive": "2020-02-17",
    "Introduction": "None",
    "LookingFor": "None",
    "Interests": "None.",
    "City": "Dhaka",
    "Country": "Bangladesh",
    "Photos": [
      {
        "url": "https://res.cloudinary.com/djysg4anm/image/upload/v1595710487/104496829_1362655707278356_3579483190794450394_n_lctdor.jpg",
        "isMain": true,
        "description": "None."
      }
    ]
  },
  
  {
    "Username": "Nimon",
    "Gender": "male",
    "DateOfBirth": "1997-02-19",
    "Password": "password",
    "KnownAs": "Nimon Hasan",
    "Created": "2020-06-27",
    "LastActive": "2020-06-27",
    "Introduction": "None",
    "LookingFor": "None",
    "Interests": "None.",
    "City": "Dhaka",
    "Country": "Bangladesh",
    "Photos": [
      {
        "url": "https://res.cloudinary.com/djysg4anm/image/upload/v1595710486/101640764_2402408566529280_2397622191131721728_o_paaom8.jpg",
        "isMain": true,
        "description": "None."
      }
    ]
  }
]